verbose_ls/__init__.py
verbose_ls/verbose_ls.py
verbose_ls-0.1.2.dist-info/METADATA
verbose_ls-0.1.2.dist-info/WHEEL
verbose_ls-0.1.2.dist-info/entry_points.txt
verbose_ls-0.1.2.dist-info/top_level.txt
verbose_ls-0.1.2.dist-info/RECORD
