Metadata-Version: 2.1
Name: verbose-ls
Version: 0.1.2
Summary: Format 'ls' output into verbose, human readable output
Home-page: https://github.com/NelsonScott/verbose_ls
License: UNKNOWN
Platform: UNKNOWN
Requires-Python: >=3.7
